[
  {
    "id": 0,
    "title": "What is an Epidemic?",
    "questions": [
      {
        "question": "What is the analogy we used to explain disease spread?",
        "options": [
          "Sharing lunch",
          "Gossip in school",
          "Tag",
          "Wearing masks"
        ],
        "correct": "Gossip in school",
        "image": "gossip.png",
        "hint": 0
      },
      {
        "question": "What tools can we use to simulate gossip spreading?",
        "options": [
          "Dice and coins",
          "Rulers",
          "Stones",
          "Maps"
        ],
        "correct": "Dice and coins",
        "image": "dice.jpg",
        "hint": 3
      },
      {
        "question": "What happens if each infected person spreads a disease to just a few more people?",
        "options": [
          "The disease slowly disappears",
          "The disease spreads faster and faster",
          "No matter what, everyone will get infected",
          "The disease is guaranteed to stop after a few days"
        ],
        "correct": "The disease spreads faster and faster",
        "image": "infection.png",
        "hint": 6
      },
      {
        "question": "Why is flipping a coin a good analogy for how a disease spreads?",
        "options": [
          "We don't know what the exact outcome of each coin-flip will be but we can still make predictions, infections work the same way",
          "Every person always spreads the disease to exactly two other people, like two sides of a coin",
          "Diseases only spread when people are playing games with coins",
          "The number of times a coin lands on heads tells us how long the disease lasts"
        ],
        "correct": "We don't know what the exact outcome of each coin-flip will be but we can still make predictions, infections work the same way",
        "image": "coin_flip.png",
        "hint": 8
      }
    ],
    "progress": 1,
    "passed": true
  },
  {
    "id": 1,
    "title": "Motivation for Epidemic Visualization",
    "questions": [
      {
        "question": "What are some goals of visualization?",
        "options": [
          "To create awareness and understanding",
          "To create awareness by inducing fear",
          "To make data more machine processable and readable",
          "To confuse people"
        ],
        "correct": "To create awareness and understanding",
        "image": "table_to_plot.png",
        "hint": 6
      }
    ],
    "progress": 1,
    "passed": true
  },
  {
    "id": 2,
    "title": "Line Plots",
    "questions": [
      {
        "question": "What is the distance between the two highlighted marks on this scale?",
        "options": [
          "50",
          "5",
          "20",
          "70"
        ],
        "correct": "50",
        "image": "scale_marked.png",
        "hint": 5
      },
      {
        "question": "According to this line plot, what was the temperature at hour 12?",
        "options": [
          "7",
          "12",
          "20",
          "4"
        ],
        "correct": "7",
        "image": "quiz_temps.png",
        "hint": 8
      },
      {
        "question": "What hour and temperature does the highlighted point represent?",
        "options": [
          "temperature: 18, hour: 3",
          "temperature: 3, hour: 18",
          "temperature: 7, hour: 18",
          "temperature: 6, hour: 0"
        ],
        "correct": "temperature: 3, hour: 18",
        "image": "quiz_temps_highlight.png",
        "hint": 9
      }
    ],
    "progress": 2,
    "passed": true
  },
  {
    "id": 3,
    "title": "Infection Trees",
    "questions": [
      {
        "question": "What is the node marked with the red dashed circle called?",
        "options": [
          "root node",
          "main node",
          "top node",
          "start node"
        ],
        "correct": "root node",
        "image": "node_quiz.png",
        "hint": 6
      },
      {
        "question": "What is the distance between the nodes 2 and 11?",
        "options": [
          "4",
          "3",
          "2",
          "1"
        ],
        "correct": "2",
        "image": "distance_quiz.png",
        "hint": 8
      },
      {
        "question": "What is the depth of this tree?",
        "options": [
          "4",
          "3",
          "2",
          "1"
        ],
        "correct": "3",
        "image": "depth_quiz.png",
        "hint": 9
      }
    ],
    "progress": 3,
    "passed": true
  },
  {
    "id": 4,
    "title": "Motivation for Epidemic Modelling",
    "questions": [
      {
        "question": "Why can it be useful to model the expected number of new infections in a day?",
        "options": [
          "To prepare hospitals for potential new patients",
          "To stop a disease from spreading",
          "To develop cures for new diseases",
          "To reduce the number of daily infections"
        ],
        "correct": "To prepare hospitals for potential new patients",
        "image": "hospital_bed.png",
        "hint": 1
      }
    ],
    "progress": 1,
    "passed": true
  },
  {
    "id": 5,
    "title": "Intro to SIR",
    "questions": [
      {
        "question": "What do S, I and R mean in the SIR model?",
        "options": [
          "S = Susceptible, I = Infectious, R = Recovered",
          "S = Sick, I = Immune, R = Removed",
          "S = Susceptible, I = Immune, R = Resistant",
          "S = Sick, I = Infectious, R = Recovered"
        ],
        "correct": "S = Susceptible, I = Infectious, R = Recovered",
        "image": "SIR.png",
        "hint": 3
      },
      {
        "question": "What is the transmission rate?",
        "options": [
          "How many people one sick person infects a day on average",
          "The rate at which people recover from the disease",
          "The speed of people moving between each compartment",
          "The initial number of infected people"
        ],
        "correct": "How many people one sick person infects a day on average",
        "image": "SIR.png",
        "hint": 9
      },
      {
        "question": "We got this plot using the SIR model to model the spread of gossip, using only the S and I compartments. We started the simulation with one person knowing about the gossip and a total of 12 people. Which of the lines shows the total number of people in the S compartment, and which shows the total number of people in the I compartment?",
        "options": [
          "The blue continuous line is S, and the orange dashed line is I",
          "The blue continuous line is I, and the orange dashed line is R",
          "None of the alternatives is correct",
          "Both lines represent the S compartment"
        ],
        "correct": "The blue continuous line is S, and the orange dashed line is I",
        "image": "SI_quiz.png",
        "hint": 11
      },
      {
        "question": "Let's say that we would like to model the spread of a disease in a school with 300 people. On the first day, 4 people were infected and started spreading the disease, and one person had already recovered from the disease. How should you set the number of people in each compartment?",
        "options": [
          "S: 300, I: 4, R: 1",
          "S: 295, I: 4, R: 1",
          "S: 299, I: 1, R: 0",
          "S: 295, I: 5, R: 0"
        ],
        "correct": "S: 295, I: 4, R: 1",
        "image": "sir_init_quiz.png",
        "hint": 19
      }
    ],
    "progress": 4,
    "passed": true
  },
  {
    "id": 6,
    "title": "Radial Trees",
    "questions": [
      {
        "question": "Test question",
        "options": [
          "7",
          "3",
          "6",
          "4"
        ],
        "correct": "6",
        "image": "rad_tree_quiz.png",
        "hint": 2
      }
    ],
    "progress": 1,
    "passed": true
  },
  {
    "id": 7,
    "title": "Intro to Agent-Based Models",
    "questions": [
      {
        "question": "Why could we need a different model instead of the SIR model?",
        "options": [
          "Because the SIR model cannot consider differences between individuals",
          "Because the SIR model takes too long to calculate for large populations",
          "Because the SIR model always predicts the exact number of sick people",
          "Because the SIR model requires expensive simulations to run"
        ],
        "correct": "Because the SIR model cannot consider differences between individuals",
        "image": "SIR.png",
        "hint": 1
      },
      {
        "question": "What is an 'agent' in agent based models?",
        "options": [
          "A group of people who are treated as if they are all the same",
          "A single individual with their own characteristics and rules",
          "A mathematical equation that predicts the spread of disease",
          "A random event like a coin flip"
        ],
        "correct": "A single individual with their own characteristics and rules",
        "image": "Agent.png",
        "hint": 2
      },
      {
        "question": "In an agent-based model, what makes an agent different from the 'beads' in the SIR analogy?",
        "options": [
          "Agents can have different characteristics and behaviors",
          "Agents cannot change state once they are infected",
          "Agents all behave exactly the same way",
          "Agents are used only for very large populations"
        ],
        "correct": "Agents can have different characteristics and behaviors",
        "image": "Friends_conn_gos.png",
        "hint": 5
      }
    ],
    "progress": 1,
    "passed": true
  },
  {
    "id": 8,
    "title": "Multi-Line Plots",
    "questions": [
      {
        "question": "What is the 'legend' of a plot?",
        "options": [
          "There is no such thing",
          "A story told by the plot",
          "An explanation of what each line in the plot represents",
          "A story that is based on a plot"
        ],
        "correct": "An explanation of what each line in the plot represents",
        "hint": 2
      },
      {
        "question": "What is important to be considered when adding multiple lines to the same plot?",
        "options": [
          "You shouldn't add more than 3 lines",
          "The lines should have similar scales",
          "You shouldn't add multiple lines to a plot",
          "Adding multiple lines is hard"
        ],
        "correct": "The lines should have similar scales",
        "hint": 3
      }
    ],
    "progress": 1,
    "passed": true
  },
  {
    "id": 9,
    "title": "SIR in Practice",
    "questions": [
      {
        "question": "What are the transitions called in our extended SIR model example?",
        "image": "SIR_vaccination_quiz.png",
        "options": [
          "a: vaccination rate, b: transmission rate, c: recovery rate",
          "a: transmission rate, b: vaccination rate, c: recovery rate",
          "a: vaccination rate, b: recovery rate, c: transmission rate",
          "a: recovery rate, b: transmission rate, c: vaccination rate"
        ],
        "correct": "a: vaccination rate, b: transmission rate, c: recovery rate",
        "hint": 7
      },
      {
        "question": "Why is it that it is not always simpler to 'just use more data' than extending our base SIR model?",
        "image": "vis_mot.png",
        "options": [
          "Because we don't always have more data",
          "Because we would have no way to visualize all the data",
          "Because the computer can't process lots of numbers",
          "Because we can't always use all the data we have"
        ],
        "correct": "Because we don't always have more data",
        "hint": 10
      }
    ],
    "progress": 1,
    "passed": true
  },
  {
    "id": 10,
    "title": "Covasim in Practice (Placeholder)",
    "questions": [
      {
        "question": "Placeholder question (correct: 1)",
        "options": [
          "1",
          "2",
          "3",
          "4"
        ],
        "correct": "1",
        "hint": 0
      }
    ],
    "progress": 1,
    "passed": true
  }
]